.gitignore
LICENSE
MANIFEST.in
README.rst
requirements.txt
run_tests.sh
setup.py
test-requirements.txt
tox.ini
tests/__init__.py
tests/unit/__init__.py
tests/unit/test_context.py
tests/unit/test_entry.py
tests/unit/test_environment.py
tests/unit/test_extensions.py
tests/unit/test_main.py
tests/unit/test_modifiers.py
tests/unit/test_steps.py
tests/unit/test_utils.py
timid/__init__.py
timid/context.py
timid/entry.py
timid/environment.py
timid/extensions.py
timid/main.py
timid/modifiers.py
timid/steps.py
timid/utils.py
timid.egg-info/PKG-INFO
timid.egg-info/SOURCES.txt
timid.egg-info/dependency_links.txt
timid.egg-info/entry_points.txt
timid.egg-info/pbr.json
timid.egg-info/requires.txt
timid.egg-info/top_level.txt