Metadata-Version: 1.1
Name: timid
Version: 0.1.2
Summary: Timid test runner
Home-page: https://github.com/rackerlabs/timid
Author: Kevin L. Mitchell
Author-email: kevin.mitchell@rackspace.com
License: Apache License (2.0)
Platform: UNKNOWN
Classifier: Development Status :: 3 - Alpha
Classifier: Environment :: Console
Classifier: License :: OSI Approved :: Apache Software License
Classifier: Programming Language :: Python
Classifier: Programming Language :: Python :: 2
Classifier: Programming Language :: Python :: 2.7
Classifier: Programming Language :: Python :: 3
Classifier: Programming Language :: Python :: 3.3
Classifier: Programming Language :: Python :: 3.4
